blender_pyutils/__init__.py
blender_pyutils/blender_wrapper.py
blender_pyutils/common.py
blender_pyutils/exceptions.py
blender_pyutils/main.py
blender_pyutils/pypi.py
blender_pyutils/utils.py
blender_pyutils/version.py
blender_pyutils-2025.7.dist-info/METADATA
blender_pyutils-2025.7.dist-info/WHEEL
blender_pyutils-2025.7.dist-info/entry_points.txt
blender_pyutils-2025.7.dist-info/licenses/LICENSE.txt
blender_pyutils-2025.7.dist-info/RECORD
