Metadata-Version: 2.4
Name: blender-pyutils
Version: 2025.7
Summary: Simple utilities for building and installing Python extensions for Blender.
Project-URL: Homepage, https://gitlab.inria.fr/jrye/blender-pyutils
Project-URL: Source, https://gitlab.inria.fr/jrye/blender-pyutils.git
Project-URL: Documentation, https://jrye.gitlabpages.inria.fr/blender-pyutils
Project-URL: Issues, https://gitlab.inria.fr/jrye/blender-pyutils/issues
Author-email: Jan-Michael Rye <jan-michael.rye@inria.fr>
License: MIT License
License-File: LICENSE.txt
Classifier: License :: OSI Approved :: MIT License
Classifier: Operating System :: OS Independent
Classifier: Programming Language :: Python :: 3
Requires-Python: >=3.7
Requires-Dist: pyxdg
Requires-Dist: tomli-w
